fishing.py
minecraft_auto_fisher-1.0.0.dist-info/METADATA
minecraft_auto_fisher-1.0.0.dist-info/WHEEL
minecraft_auto_fisher-1.0.0.dist-info/entry_points.txt
minecraft_auto_fisher-1.0.0.dist-info/top_level.txt
minecraft_auto_fisher-1.0.0.dist-info/RECORD
