Metadata-Version: 2.1
Name: minecraft-auto-fisher
Version: 1.0.0
Summary: A python module to automaticaly fish in Minecraft
Home-page: https://github.com/elias123tre/minecraft-auto-fisher
Author: elias123tre
License: UNKNOWN
Platform: UNKNOWN
Requires-Python: >=3.6
Requires-Dist: keyboard
Requires-Dist: pyautogui
Requires-Dist: requests
Requires-Dist: pillow
Requires-Dist: opencv-python
